mcp_greeting/__init__.py
mcp_greeting/__main__.py
mcp_greeting/server.py
mcp_greeting-0.1.3.dist-info/METADATA
mcp_greeting-0.1.3.dist-info/WHEEL
mcp_greeting-0.1.3.dist-info/entry_points.txt
mcp_greeting-0.1.3.dist-info/RECORD
