Metadata-Version: 2.4
Name: mcp-greeting
Version: 0.1.3
Summary: A simple greeting MCP server
Requires-Python: >=3.10
Requires-Dist: mcp[cli]>=1.6.0
